{
  "appInfo" : {
    "build" : "241.15989.150",
    "buildDate" : "2024-04-29T11:42:00Z[UTC]",
    "productCode" : "IC",
    "generated" : "2024-05-08T01:27:37.425852013Z",
    "os" : "Linux 6.5.0-28-generic",
    "runtime" : "JetBrains s.r.o. 17.0.10 17.0.10+1-b1207.14"
  },
  "runtimeInfo" : {
    "maxMemory" : 2147483648,
    "numberOfProcessors" : 12,
    "maxNumberOfIndexingThreads" : 11,
    "maxSizeOfFileForIntelliSense" : 2560000,
    "maxSizeOfFileForContentLoading" : 20971520
  },
  "type" : "Scanning",
  "projectIndexingActivityHistory" : {
    "projectName" : "ChatApp_CodeMaster",
    "times" : {
      "scanningReason" : "On project open",
      "scanningType" : "FULL_ON_PROJECT_OPEN",
      "scanningId" : 4,
      "creatingIteratorsTime" : 1041731,
      "concurrentHandlingWallTimeWithoutPauses" : 97833872,
      "concurrentHandlingWallTimeWithPauses" : 97833872,
      "concurrentHandlingSumOfThreadTimesWithPauses" : 122608019,
      "concurrentIterationAndScannersApplicationSumOfThreadTimesWithPauses" : 63799292,
      "concurrentFileCheckSumOfThreadTimesWithPauses" : 58137350,
      "delayedPushPropertiesStageTime" : 7364,
      "indexExtensionsTime" : 0,
      "dumbWallTimeWithPauses" : 0,
      "dumbWallTimeWithoutPauses" : 0,
      "updatingStart" : "2024-05-08T01:27:37.321132771Z",
      "updatingEnd" : "2024-05-08T01:27:37.42375141Z",
      "totalWallTimeWithPauses" : 102620343,
      "wallTimeOnPause" : 0,
      "wasInterrupted" : false,
      "totalWallTimeWithoutPauses" : 102620343
    },
    "fileCount" : {
      "numberOfFileProviders" : 19,
      "numberOfScannedFiles" : 81135,
      "numberOfFilesIndexedByInfrastructureExtensionsDuringScan" : 0,
      "numberOfFilesScheduledForIndexingAfterScan" : 0
    },
    "scanningStatistics" : [ {
      "providerName" : "JDK 11 /home/fayek/.jdks/openjdk-22.0.1",
      "numberOfScannedFiles" : 75046,
      "numberOfSkippedFiles" : 0,
      "numberOfFilesForIndexing" : 0,
      "numberOfFilesFullyIndexedByInfrastructureExtensions" : 0,
      "filesFullyIndexedByInfrastructureExtensions" : [ ],
      "statusTime" : 25407921,
      "totalOneThreadTimeWithPauses" : 94318126,
      "iterationAndScannersApplicationTime" : 45605714,
      "filesCheckTime" : 48676205,
      "timeProcessingUpToDateFiles" : 0,
      "timeUpdatingContentLessIndexes" : 0,
      "timeIndexingWithoutContentViaInfrastructureExtension" : 0,
      "roots" : [ ]
    }, {
      "providerName" : "Library Maven: org.openjfx:javafx-graphics:linux:18.0.2 (#1 class roots, #0 source roots)",
      "numberOfScannedFiles" : 3180,
      "numberOfSkippedFiles" : 0,
      "numberOfFilesForIndexing" : 0,
      "numberOfFilesFullyIndexedByInfrastructureExtensions" : 0,
      "filesFullyIndexedByInfrastructureExtensions" : [ ],
      "statusTime" : 2105635,
      "totalOneThreadTimeWithPauses" : 10664936,
      "iterationAndScannersApplicationTime" : 7004061,
      "filesCheckTime" : 3623176,
      "timeProcessingUpToDateFiles" : 0,
      "timeUpdatingContentLessIndexes" : 0,
      "timeIndexingWithoutContentViaInfrastructureExtension" : 0,
      "roots" : [ ]
    }, {
      "providerName" : "Library Maven: org.openjfx:javafx-controls:linux:18.0.2 (#1 class roots, #0 source roots)",
      "numberOfScannedFiles" : 1486,
      "numberOfSkippedFiles" : 0,
      "numberOfFilesForIndexing" : 0,
      "numberOfFilesFullyIndexedByInfrastructureExtensions" : 0,
      "filesFullyIndexedByInfrastructureExtensions" : [ ],
      "statusTime" : 308429,
      "totalOneThreadTimeWithPauses" : 5510764,
      "iterationAndScannersApplicationTime" : 4979489,
      "filesCheckTime" : 488025,
      "timeProcessingUpToDateFiles" : 0,
      "timeUpdatingContentLessIndexes" : 0,
      "timeIndexingWithoutContentViaInfrastructureExtension" : 0,
      "roots" : [ ]
    }, {
      "providerName" : "Module 'EChat' (all roots)",
      "numberOfScannedFiles" : 29,
      "numberOfSkippedFiles" : 0,
      "numberOfFilesForIndexing" : 0,
      "numberOfFilesFullyIndexedByInfrastructureExtensions" : 0,
      "filesFullyIndexedByInfrastructureExtensions" : [ ],
      "statusTime" : 1492979,
      "totalOneThreadTimeWithPauses" : 4254585,
      "iterationAndScannersApplicationTime" : 601115,
      "filesCheckTime" : 3584083,
      "timeProcessingUpToDateFiles" : 85651,
      "timeUpdatingContentLessIndexes" : 0,
      "timeIndexingWithoutContentViaInfrastructureExtension" : 0,
      "roots" : [ ]
    }, {
      "providerName" : "Library Maven: org.openjfx:javafx-base:linux:18.0.2 (#1 class roots, #0 source roots)",
      "numberOfScannedFiles" : 666,
      "numberOfSkippedFiles" : 0,
      "numberOfFilesForIndexing" : 0,
      "numberOfFilesFullyIndexedByInfrastructureExtensions" : 0,
      "filesFullyIndexedByInfrastructureExtensions" : [ ],
      "statusTime" : 228172,
      "totalOneThreadTimeWithPauses" : 4050768,
      "iterationAndScannersApplicationTime" : 3582289,
      "filesCheckTime" : 435828,
      "timeProcessingUpToDateFiles" : 0,
      "timeUpdatingContentLessIndexes" : 0,
      "timeIndexingWithoutContentViaInfrastructureExtension" : 0,
      "roots" : [ ]
    }, {
      "providerName" : "Library Maven: com.jfoenix:jfoenix:9.0.1 (#1 class roots, #0 source roots)",
      "numberOfScannedFiles" : 341,
      "numberOfSkippedFiles" : 0,
      "numberOfFilesForIndexing" : 0,
      "numberOfFilesFullyIndexedByInfrastructureExtensions" : 0,
      "filesFullyIndexedByInfrastructureExtensions" : [ ],
      "statusTime" : 92992,
      "totalOneThreadTimeWithPauses" : 1060616,
      "iterationAndScannersApplicationTime" : 851838,
      "filesCheckTime" : 183580,
      "timeProcessingUpToDateFiles" : 0,
      "timeUpdatingContentLessIndexes" : 0,
      "timeIndexingWithoutContentViaInfrastructureExtension" : 0,
      "roots" : [ ]
    }, {
      "providerName" : "Library Maven: com.vdurmont:emoji-java:5.1.1 (#1 class roots, #0 source roots)",
      "numberOfScannedFiles" : 26,
      "numberOfSkippedFiles" : 0,
      "numberOfFilesForIndexing" : 0,
      "numberOfFilesFullyIndexedByInfrastructureExtensions" : 0,
      "filesFullyIndexedByInfrastructureExtensions" : [ ],
      "statusTime" : 8047,
      "totalOneThreadTimeWithPauses" : 536965,
      "iterationAndScannersApplicationTime" : 175555,
      "filesCheckTime" : 320014,
      "timeProcessingUpToDateFiles" : 0,
      "timeUpdatingContentLessIndexes" : 0,
      "timeIndexingWithoutContentViaInfrastructureExtension" : 0,
      "roots" : [ ]
    }, {
      "providerName" : "Library Maven: org.openjfx:javafx-controls:18.0.2 (#1 class roots, #0 source roots)",
      "numberOfScannedFiles" : 1,
      "numberOfSkippedFiles" : 0,
      "numberOfFilesForIndexing" : 0,
      "numberOfFilesFullyIndexedByInfrastructureExtensions" : 0,
      "filesFullyIndexedByInfrastructureExtensions" : [ ],
      "statusTime" : 701,
      "totalOneThreadTimeWithPauses" : 523750,
      "iterationAndScannersApplicationTime" : 209659,
      "filesCheckTime" : 272425,
      "timeProcessingUpToDateFiles" : 0,
      "timeUpdatingContentLessIndexes" : 0,
      "timeIndexingWithoutContentViaInfrastructureExtension" : 0,
      "roots" : [ ]
    }, {
      "providerName" : "Library Maven: org.openjfx:javafx-fxml:linux:18.0.2 (#1 class roots, #1 source roots)",
      "numberOfScannedFiles" : 81,
      "numberOfSkippedFiles" : 1,
      "numberOfFilesForIndexing" : 0,
      "numberOfFilesFullyIndexedByInfrastructureExtensions" : 0,
      "filesFullyIndexedByInfrastructureExtensions" : [ ],
      "statusTime" : 27830,
      "totalOneThreadTimeWithPauses" : 510606,
      "iterationAndScannersApplicationTime" : 291039,
      "filesCheckTime" : 74759,
      "timeProcessingUpToDateFiles" : 0,
      "timeUpdatingContentLessIndexes" : 0,
      "timeIndexingWithoutContentViaInfrastructureExtension" : 0,
      "roots" : [ ]
    }, {
      "providerName" : "Indexable set contributor 'com.intellij.javaee.ExternalResourcesRootsProvider@346786dd' (non-project)",
      "numberOfScannedFiles" : 215,
      "numberOfSkippedFiles" : 4,
      "numberOfFilesForIndexing" : 0,
      "numberOfFilesFullyIndexedByInfrastructureExtensions" : 0,
      "filesFullyIndexedByInfrastructureExtensions" : [ ],
      "statusTime" : 64787,
      "totalOneThreadTimeWithPauses" : 353345,
      "iterationAndScannersApplicationTime" : 204378,
      "filesCheckTime" : 130101,
      "timeProcessingUpToDateFiles" : 0,
      "timeUpdatingContentLessIndexes" : 0,
      "timeIndexingWithoutContentViaInfrastructureExtension" : 0,
      "roots" : [ ]
    }, {
      "providerName" : "Library Maven: org.openjfx:javafx-fxml:18.0.2 (#1 class roots, #1 source roots)",
      "numberOfScannedFiles" : 29,
      "numberOfSkippedFiles" : 0,
      "numberOfFilesForIndexing" : 0,
      "numberOfFilesFullyIndexedByInfrastructureExtensions" : 0,
      "filesFullyIndexedByInfrastructureExtensions" : [ ],
      "statusTime" : 8504,
      "totalOneThreadTimeWithPauses" : 224726,
      "iterationAndScannersApplicationTime" : 118550,
      "filesCheckTime" : 84386,
      "timeProcessingUpToDateFiles" : 0,
      "timeUpdatingContentLessIndexes" : 0,
      "timeIndexingWithoutContentViaInfrastructureExtension" : 0,
      "roots" : [ ]
    }, {
      "providerName" : "Library Maven: org.json:json:20170516 (#1 class roots, #0 source roots)",
      "numberOfScannedFiles" : 26,
      "numberOfSkippedFiles" : 0,
      "numberOfFilesForIndexing" : 0,
      "numberOfFilesFullyIndexedByInfrastructureExtensions" : 0,
      "filesFullyIndexedByInfrastructureExtensions" : [ ],
      "statusTime" : 17764,
      "totalOneThreadTimeWithPauses" : 204760,
      "iterationAndScannersApplicationTime" : 97000,
      "filesCheckTime" : 74528,
      "timeProcessingUpToDateFiles" : 0,
      "timeUpdatingContentLessIndexes" : 0,
      "timeIndexingWithoutContentViaInfrastructureExtension" : 0,
      "roots" : [ ]
    }, {
      "providerName" : "Library Maven: org.openjfx:javafx-graphics:18.0.2 (#1 class roots, #0 source roots)",
      "numberOfScannedFiles" : 1,
      "numberOfSkippedFiles" : 0,
      "numberOfFilesForIndexing" : 0,
      "numberOfFilesFullyIndexedByInfrastructureExtensions" : 0,
      "filesFullyIndexedByInfrastructureExtensions" : [ ],
      "statusTime" : 380,
      "totalOneThreadTimeWithPauses" : 120664,
      "iterationAndScannersApplicationTime" : 24075,
      "filesCheckTime" : 70100,
      "timeProcessingUpToDateFiles" : 0,
      "timeUpdatingContentLessIndexes" : 0,
      "timeIndexingWithoutContentViaInfrastructureExtension" : 0,
      "roots" : [ ]
    }, {
      "providerName" : "Library Maven: org.openjfx:javafx-base:18.0.2 (#1 class roots, #0 source roots)",
      "numberOfScannedFiles" : 1,
      "numberOfSkippedFiles" : 0,
      "numberOfFilesForIndexing" : 0,
      "numberOfFilesFullyIndexedByInfrastructureExtensions" : 0,
      "filesFullyIndexedByInfrastructureExtensions" : [ ],
      "statusTime" : 331,
      "totalOneThreadTimeWithPauses" : 57166,
      "iterationAndScannersApplicationTime" : 18845,
      "filesCheckTime" : 21329,
      "timeProcessingUpToDateFiles" : 0,
      "timeUpdatingContentLessIndexes" : 0,
      "timeIndexingWithoutContentViaInfrastructureExtension" : 0,
      "roots" : [ ]
    }, {
      "providerName" : "Indexable set contributor 'Scratches & Consoles' (project)",
      "numberOfScannedFiles" : 0,
      "numberOfSkippedFiles" : 0,
      "numberOfFilesForIndexing" : 0,
      "numberOfFilesFullyIndexedByInfrastructureExtensions" : 0,
      "filesFullyIndexedByInfrastructureExtensions" : [ ],
      "statusTime" : 0,
      "totalOneThreadTimeWithPauses" : 53349,
      "iterationAndScannersApplicationTime" : 6001,
      "filesCheckTime" : 23403,
      "timeProcessingUpToDateFiles" : 0,
      "timeUpdatingContentLessIndexes" : 0,
      "timeIndexingWithoutContentViaInfrastructureExtension" : 0,
      "roots" : [ ]
    }, {
      "providerName" : "Indexable set contributor 'org.jetbrains.kotlin.idea.base.indices.contributors.BuiltInsIndexableSetContributor@5ba32824' (non-project)",
      "numberOfScannedFiles" : 7,
      "numberOfSkippedFiles" : 0,
      "numberOfFilesForIndexing" : 0,
      "numberOfFilesFullyIndexedByInfrastructureExtensions" : 0,
      "filesFullyIndexedByInfrastructureExtensions" : [ ],
      "statusTime" : 4301,
      "totalOneThreadTimeWithPauses" : 45054,
      "iterationAndScannersApplicationTime" : 13926,
      "filesCheckTime" : 20357,
      "timeProcessingUpToDateFiles" : 0,
      "timeUpdatingContentLessIndexes" : 0,
      "timeIndexingWithoutContentViaInfrastructureExtension" : 0,
      "roots" : [ ]
    }, {
      "providerName" : "Indexable set contributor 'Scratches & Consoles' (non-project)",
      "numberOfScannedFiles" : 0,
      "numberOfSkippedFiles" : 0,
      "numberOfFilesForIndexing" : 0,
      "numberOfFilesFullyIndexedByInfrastructureExtensions" : 0,
      "filesFullyIndexedByInfrastructureExtensions" : [ ],
      "statusTime" : 0,
      "totalOneThreadTimeWithPauses" : 44793,
      "iterationAndScannersApplicationTime" : 6652,
      "filesCheckTime" : 17883,
      "timeProcessingUpToDateFiles" : 0,
      "timeUpdatingContentLessIndexes" : 0,
      "timeIndexingWithoutContentViaInfrastructureExtension" : 0,
      "roots" : [ ]
    }, {
      "providerName" : "Indexable set contributor 'org.jetbrains.kotlin.idea.base.indices.contributors.BuiltInsIndexableSetContributor@5ba32824' (project)",
      "numberOfScannedFiles" : 0,
      "numberOfSkippedFiles" : 0,
      "numberOfFilesForIndexing" : 0,
      "numberOfFilesFullyIndexedByInfrastructureExtensions" : 0,
      "filesFullyIndexedByInfrastructureExtensions" : [ ],
      "statusTime" : 0,
      "totalOneThreadTimeWithPauses" : 38101,
      "iterationAndScannersApplicationTime" : 5129,
      "filesCheckTime" : 19706,
      "timeProcessingUpToDateFiles" : 0,
      "timeUpdatingContentLessIndexes" : 0,
      "timeIndexingWithoutContentViaInfrastructureExtension" : 0,
      "roots" : [ ]
    }, {
      "providerName" : "Indexable set contributor 'com.intellij.javaee.ExternalResourcesRootsProvider@346786dd' (project)",
      "numberOfScannedFiles" : 0,
      "numberOfSkippedFiles" : 0,
      "numberOfFilesForIndexing" : 0,
      "numberOfFilesFullyIndexedByInfrastructureExtensions" : 0,
      "filesFullyIndexedByInfrastructureExtensions" : [ ],
      "statusTime" : 0,
      "totalOneThreadTimeWithPauses" : 34945,
      "iterationAndScannersApplicationTime" : 3977,
      "filesCheckTime" : 17462,
      "timeProcessingUpToDateFiles" : 0,
      "timeUpdatingContentLessIndexes" : 0,
      "timeIndexingWithoutContentViaInfrastructureExtension" : 0,
      "roots" : [ ]
    } ]
  }
}