{
  "appInfo" : {
    "build" : "241.15989.150",
    "buildDate" : "2024-04-29T11:42:00Z[UTC]",
    "productCode" : "IC",
    "generated" : "2024-05-08T16:22:29.858959184Z",
    "os" : "Linux 6.5.0-28-generic",
    "runtime" : "JetBrains s.r.o. 17.0.10 17.0.10+1-b1207.14"
  },
  "runtimeInfo" : {
    "maxMemory" : 2147483648,
    "numberOfProcessors" : 12,
    "maxNumberOfIndexingThreads" : 11,
    "maxSizeOfFileForIntelliSense" : 2560000,
    "maxSizeOfFileForContentLoading" : 20971520
  },
  "type" : "Scanning",
  "projectIndexingActivityHistory" : {
    "projectName" : "ChatApp_CodeMaster",
    "times" : {
      "scanningReason" : "On project open",
      "scanningType" : "FULL_ON_PROJECT_OPEN",
      "scanningId" : 1,
      "creatingIteratorsTime" : 11571309,
      "concurrentHandlingWallTimeWithoutPauses" : 655608007,
      "concurrentHandlingWallTimeWithPauses" : 655608007,
      "concurrentHandlingSumOfThreadTimesWithPauses" : 1036325980,
      "concurrentIterationAndScannersApplicationSumOfThreadTimesWithPauses" : 845311662,
      "concurrentFileCheckSumOfThreadTimesWithPauses" : 189023171,
      "delayedPushPropertiesStageTime" : 5119,
      "indexExtensionsTime" : 0,
      "dumbWallTimeWithPauses" : 0,
      "dumbWallTimeWithoutPauses" : 0,
      "updatingStart" : "2024-05-08T16:22:29.16162177Z",
      "updatingEnd" : "2024-05-08T16:22:29.857886224Z",
      "totalWallTimeWithPauses" : 696267398,
      "wallTimeOnPause" : 0,
      "wasInterrupted" : false,
      "totalWallTimeWithoutPauses" : 696267398
    },
    "fileCount" : {
      "numberOfFileProviders" : 19,
      "numberOfScannedFiles" : 81139,
      "numberOfFilesIndexedByInfrastructureExtensionsDuringScan" : 0,
      "numberOfFilesScheduledForIndexingAfterScan" : 0
    },
    "scanningStatistics" : [ {
      "providerName" : "JDK 11 /home/fayek/.jdks/openjdk-22.0.1",
      "numberOfScannedFiles" : 75046,
      "numberOfSkippedFiles" : 0,
      "numberOfFilesForIndexing" : 0,
      "numberOfFilesFullyIndexedByInfrastructureExtensions" : 0,
      "filesFullyIndexedByInfrastructureExtensions" : [ ],
      "statusTime" : 27243099,
      "totalOneThreadTimeWithPauses" : 639082708,
      "iterationAndScannersApplicationTime" : 604012346,
      "filesCheckTime" : 34952568,
      "timeProcessingUpToDateFiles" : 2793223,
      "timeUpdatingContentLessIndexes" : 0,
      "timeIndexingWithoutContentViaInfrastructureExtension" : 0,
      "roots" : [ ]
    }, {
      "providerName" : "Library Maven: org.openjfx:javafx-graphics:linux:18.0.2 (#1 class roots, #0 source roots)",
      "numberOfScannedFiles" : 3180,
      "numberOfSkippedFiles" : 0,
      "numberOfFilesForIndexing" : 0,
      "numberOfFilesFullyIndexedByInfrastructureExtensions" : 0,
      "filesFullyIndexedByInfrastructureExtensions" : [ ],
      "statusTime" : 8860473,
      "totalOneThreadTimeWithPauses" : 92627572,
      "iterationAndScannersApplicationTime" : 82424066,
      "filesCheckTime" : 9765804,
      "timeProcessingUpToDateFiles" : 1135248,
      "timeUpdatingContentLessIndexes" : 0,
      "timeIndexingWithoutContentViaInfrastructureExtension" : 0,
      "roots" : [ ]
    }, {
      "providerName" : "Module 'EChat' (all roots)",
      "numberOfScannedFiles" : 33,
      "numberOfSkippedFiles" : 0,
      "numberOfFilesForIndexing" : 0,
      "numberOfFilesFullyIndexedByInfrastructureExtensions" : 0,
      "filesFullyIndexedByInfrastructureExtensions" : [ ],
      "statusTime" : 70562157,
      "totalOneThreadTimeWithPauses" : 90195947,
      "iterationAndScannersApplicationTime" : 15668070,
      "filesCheckTime" : 74401176,
      "timeProcessingUpToDateFiles" : 1163834,
      "timeUpdatingContentLessIndexes" : 0,
      "timeIndexingWithoutContentViaInfrastructureExtension" : 0,
      "roots" : [ ]
    }, {
      "providerName" : "Library Maven: org.openjfx:javafx-controls:linux:18.0.2 (#1 class roots, #0 source roots)",
      "numberOfScannedFiles" : 1486,
      "numberOfSkippedFiles" : 0,
      "numberOfFilesForIndexing" : 0,
      "numberOfFilesFullyIndexedByInfrastructureExtensions" : 0,
      "filesFullyIndexedByInfrastructureExtensions" : [ ],
      "statusTime" : 13553216,
      "totalOneThreadTimeWithPauses" : 60885380,
      "iterationAndScannersApplicationTime" : 36934086,
      "filesCheckTime" : 23894836,
      "timeProcessingUpToDateFiles" : 0,
      "timeUpdatingContentLessIndexes" : 0,
      "timeIndexingWithoutContentViaInfrastructureExtension" : 0,
      "roots" : [ ]
    }, {
      "providerName" : "Library Maven: org.openjfx:javafx-base:linux:18.0.2 (#1 class roots, #0 source roots)",
      "numberOfScannedFiles" : 666,
      "numberOfSkippedFiles" : 0,
      "numberOfFilesForIndexing" : 0,
      "numberOfFilesFullyIndexedByInfrastructureExtensions" : 0,
      "filesFullyIndexedByInfrastructureExtensions" : [ ],
      "statusTime" : 13721134,
      "totalOneThreadTimeWithPauses" : 57171537,
      "iterationAndScannersApplicationTime" : 32154535,
      "filesCheckTime" : 24958310,
      "timeProcessingUpToDateFiles" : 0,
      "timeUpdatingContentLessIndexes" : 0,
      "timeIndexingWithoutContentViaInfrastructureExtension" : 0,
      "roots" : [ ]
    }, {
      "providerName" : "Library Maven: com.jfoenix:jfoenix:9.0.1 (#1 class roots, #0 source roots)",
      "numberOfScannedFiles" : 341,
      "numberOfSkippedFiles" : 0,
      "numberOfFilesForIndexing" : 0,
      "numberOfFilesFullyIndexedByInfrastructureExtensions" : 0,
      "filesFullyIndexedByInfrastructureExtensions" : [ ],
      "statusTime" : 1288849,
      "totalOneThreadTimeWithPauses" : 24895330,
      "iterationAndScannersApplicationTime" : 22354697,
      "filesCheckTime" : 2473374,
      "timeProcessingUpToDateFiles" : 0,
      "timeUpdatingContentLessIndexes" : 0,
      "timeIndexingWithoutContentViaInfrastructureExtension" : 0,
      "roots" : [ ]
    }, {
      "providerName" : "Library Maven: com.vdurmont:emoji-java:5.1.1 (#1 class roots, #0 source roots)",
      "numberOfScannedFiles" : 26,
      "numberOfSkippedFiles" : 0,
      "numberOfFilesForIndexing" : 0,
      "numberOfFilesFullyIndexedByInfrastructureExtensions" : 0,
      "filesFullyIndexedByInfrastructureExtensions" : [ ],
      "statusTime" : 129792,
      "totalOneThreadTimeWithPauses" : 13272023,
      "iterationAndScannersApplicationTime" : 12914162,
      "filesCheckTime" : 288379,
      "timeProcessingUpToDateFiles" : 0,
      "timeUpdatingContentLessIndexes" : 0,
      "timeIndexingWithoutContentViaInfrastructureExtension" : 0,
      "roots" : [ ]
    }, {
      "providerName" : "Library Maven: org.openjfx:javafx-fxml:18.0.2 (#1 class roots, #1 source roots)",
      "numberOfScannedFiles" : 29,
      "numberOfSkippedFiles" : 0,
      "numberOfFilesForIndexing" : 0,
      "numberOfFilesFullyIndexedByInfrastructureExtensions" : 0,
      "filesFullyIndexedByInfrastructureExtensions" : [ ],
      "statusTime" : 170995,
      "totalOneThreadTimeWithPauses" : 12808711,
      "iterationAndScannersApplicationTime" : 12380377,
      "filesCheckTime" : 393979,
      "timeProcessingUpToDateFiles" : 0,
      "timeUpdatingContentLessIndexes" : 0,
      "timeIndexingWithoutContentViaInfrastructureExtension" : 0,
      "roots" : [ ]
    }, {
      "providerName" : "Library Maven: org.openjfx:javafx-fxml:linux:18.0.2 (#1 class roots, #1 source roots)",
      "numberOfScannedFiles" : 81,
      "numberOfSkippedFiles" : 1,
      "numberOfFilesForIndexing" : 0,
      "numberOfFilesFullyIndexedByInfrastructureExtensions" : 0,
      "filesFullyIndexedByInfrastructureExtensions" : [ ],
      "statusTime" : 470108,
      "totalOneThreadTimeWithPauses" : 11841922,
      "iterationAndScannersApplicationTime" : 10972509,
      "filesCheckTime" : 833085,
      "timeProcessingUpToDateFiles" : 0,
      "timeUpdatingContentLessIndexes" : 0,
      "timeIndexingWithoutContentViaInfrastructureExtension" : 0,
      "roots" : [ ]
    }, {
      "providerName" : "Library Maven: org.json:json:20170516 (#1 class roots, #0 source roots)",
      "numberOfScannedFiles" : 26,
      "numberOfSkippedFiles" : 0,
      "numberOfFilesForIndexing" : 0,
      "numberOfFilesFullyIndexedByInfrastructureExtensions" : 0,
      "filesFullyIndexedByInfrastructureExtensions" : [ ],
      "statusTime" : 290088,
      "totalOneThreadTimeWithPauses" : 10156857,
      "iterationAndScannersApplicationTime" : 9531849,
      "filesCheckTime" : 472910,
      "timeProcessingUpToDateFiles" : 0,
      "timeUpdatingContentLessIndexes" : 0,
      "timeIndexingWithoutContentViaInfrastructureExtension" : 0,
      "roots" : [ ]
    }, {
      "providerName" : "Library Maven: org.openjfx:javafx-controls:18.0.2 (#1 class roots, #0 source roots)",
      "numberOfScannedFiles" : 1,
      "numberOfSkippedFiles" : 0,
      "numberOfFilesForIndexing" : 0,
      "numberOfFilesFullyIndexedByInfrastructureExtensions" : 0,
      "filesFullyIndexedByInfrastructureExtensions" : [ ],
      "statusTime" : 4989,
      "totalOneThreadTimeWithPauses" : 9715959,
      "iterationAndScannersApplicationTime" : 2692221,
      "filesCheckTime" : 6971930,
      "timeProcessingUpToDateFiles" : 0,
      "timeUpdatingContentLessIndexes" : 0,
      "timeIndexingWithoutContentViaInfrastructureExtension" : 0,
      "roots" : [ ]
    }, {
      "providerName" : "Library Maven: org.openjfx:javafx-graphics:18.0.2 (#1 class roots, #0 source roots)",
      "numberOfScannedFiles" : 1,
      "numberOfSkippedFiles" : 0,
      "numberOfFilesForIndexing" : 0,
      "numberOfFilesFullyIndexedByInfrastructureExtensions" : 0,
      "filesFullyIndexedByInfrastructureExtensions" : [ ],
      "statusTime" : 4228,
      "totalOneThreadTimeWithPauses" : 8441304,
      "iterationAndScannersApplicationTime" : 1506536,
      "filesCheckTime" : 6879945,
      "timeProcessingUpToDateFiles" : 0,
      "timeUpdatingContentLessIndexes" : 0,
      "timeIndexingWithoutContentViaInfrastructureExtension" : 0,
      "roots" : [ ]
    }, {
      "providerName" : "Indexable set contributor 'com.intellij.javaee.ExternalResourcesRootsProvider@15ea2249' (non-project)",
      "numberOfScannedFiles" : 215,
      "numberOfSkippedFiles" : 4,
      "numberOfFilesForIndexing" : 0,
      "numberOfFilesFullyIndexedByInfrastructureExtensions" : 0,
      "filesFullyIndexedByInfrastructureExtensions" : [ ],
      "statusTime" : 977325,
      "totalOneThreadTimeWithPauses" : 3558689,
      "iterationAndScannersApplicationTime" : 1329419,
      "filesCheckTime" : 2202268,
      "timeProcessingUpToDateFiles" : 0,
      "timeUpdatingContentLessIndexes" : 0,
      "timeIndexingWithoutContentViaInfrastructureExtension" : 0,
      "roots" : [ ]
    }, {
      "providerName" : "Indexable set contributor 'org.jetbrains.kotlin.idea.base.indices.contributors.BuiltInsIndexableSetContributor@27c4304' (non-project)",
      "numberOfScannedFiles" : 7,
      "numberOfSkippedFiles" : 0,
      "numberOfFilesForIndexing" : 0,
      "numberOfFilesFullyIndexedByInfrastructureExtensions" : 0,
      "filesFullyIndexedByInfrastructureExtensions" : [ ],
      "statusTime" : 60375,
      "totalOneThreadTimeWithPauses" : 1003068,
      "iterationAndScannersApplicationTime" : 173871,
      "filesCheckTime" : 268721,
      "timeProcessingUpToDateFiles" : 0,
      "timeUpdatingContentLessIndexes" : 0,
      "timeIndexingWithoutContentViaInfrastructureExtension" : 0,
      "roots" : [ ]
    }, {
      "providerName" : "Library Maven: org.openjfx:javafx-base:18.0.2 (#1 class roots, #0 source roots)",
      "numberOfScannedFiles" : 1,
      "numberOfSkippedFiles" : 0,
      "numberOfFilesForIndexing" : 0,
      "numberOfFilesFullyIndexedByInfrastructureExtensions" : 0,
      "filesFullyIndexedByInfrastructureExtensions" : [ ],
      "statusTime" : 4509,
      "totalOneThreadTimeWithPauses" : 345407,
      "iterationAndScannersApplicationTime" : 228915,
      "filesCheckTime" : 63080,
      "timeProcessingUpToDateFiles" : 0,
      "timeUpdatingContentLessIndexes" : 0,
      "timeIndexingWithoutContentViaInfrastructureExtension" : 0,
      "roots" : [ ]
    }, {
      "providerName" : "Indexable set contributor 'Scratches & Consoles' (project)",
      "numberOfScannedFiles" : 0,
      "numberOfSkippedFiles" : 0,
      "numberOfFilesForIndexing" : 0,
      "numberOfFilesFullyIndexedByInfrastructureExtensions" : 0,
      "filesFullyIndexedByInfrastructureExtensions" : [ ],
      "statusTime" : 0,
      "totalOneThreadTimeWithPauses" : 179131,
      "iterationAndScannersApplicationTime" : 17843,
      "filesCheckTime" : 128204,
      "timeProcessingUpToDateFiles" : 0,
      "timeUpdatingContentLessIndexes" : 0,
      "timeIndexingWithoutContentViaInfrastructureExtension" : 0,
      "roots" : [ ]
    }, {
      "providerName" : "Indexable set contributor 'org.jetbrains.kotlin.idea.base.indices.contributors.BuiltInsIndexableSetContributor@27c4304' (project)",
      "numberOfScannedFiles" : 0,
      "numberOfSkippedFiles" : 0,
      "numberOfFilesForIndexing" : 0,
      "numberOfFilesFullyIndexedByInfrastructureExtensions" : 0,
      "filesFullyIndexedByInfrastructureExtensions" : [ ],
      "statusTime" : 0,
      "totalOneThreadTimeWithPauses" : 52039,
      "iterationAndScannersApplicationTime" : 6031,
      "filesCheckTime" : 24346,
      "timeProcessingUpToDateFiles" : 0,
      "timeUpdatingContentLessIndexes" : 0,
      "timeIndexingWithoutContentViaInfrastructureExtension" : 0,
      "roots" : [ ]
    }, {
      "providerName" : "Indexable set contributor 'Scratches & Consoles' (non-project)",
      "numberOfScannedFiles" : 0,
      "numberOfSkippedFiles" : 0,
      "numberOfFilesForIndexing" : 0,
      "numberOfFilesFullyIndexedByInfrastructureExtensions" : 0,
      "filesFullyIndexedByInfrastructureExtensions" : [ ],
      "statusTime" : 0,
      "totalOneThreadTimeWithPauses" : 51318,
      "iterationAndScannersApplicationTime" : 5350,
      "filesCheckTime" : 28585,
      "timeProcessingUpToDateFiles" : 0,
      "timeUpdatingContentLessIndexes" : 0,
      "timeIndexingWithoutContentViaInfrastructureExtension" : 0,
      "roots" : [ ]
    }, {
      "providerName" : "Indexable set contributor 'com.intellij.javaee.ExternalResourcesRootsProvider@15ea2249' (project)",
      "numberOfScannedFiles" : 0,
      "numberOfSkippedFiles" : 0,
      "numberOfFilesForIndexing" : 0,
      "numberOfFilesFullyIndexedByInfrastructureExtensions" : 0,
      "filesFullyIndexedByInfrastructureExtensions" : [ ],
      "statusTime" : 0,
      "totalOneThreadTimeWithPauses" : 41078,
      "iterationAndScannersApplicationTime" : 4779,
      "filesCheckTime" : 21671,
      "timeProcessingUpToDateFiles" : 0,
      "timeUpdatingContentLessIndexes" : 0,
      "timeIndexingWithoutContentViaInfrastructureExtension" : 0,
      "roots" : [ ]
    } ]
  }
}